inject_javascript/__init__.py
inject_javascript/cli.py
inject_javascript/lib/__init__.py
inject_javascript-0.0.8.dist-info/LICENSE
inject_javascript-0.0.8.dist-info/METADATA
inject_javascript-0.0.8.dist-info/WHEEL
inject_javascript-0.0.8.dist-info/entry_points.txt
inject_javascript-0.0.8.dist-info/top_level.txt
inject_javascript-0.0.8.dist-info/RECORD
