Metadata-Version: 2.1
Name: inject-javascript
Version: 0.0.8
Summary: Inject JavaScript within PDF document body
Home-page: https://github.com/pdf-utilities/inject_javascript
Author: S0AndS0
Author-email: StrangerThanBland@gmail.com
License: UNKNOWN
Platform: UNKNOWN
Classifier: Development Status :: 3 - Alpha
Classifier: Intended Audience :: Developers
Classifier: Topic :: Software Development :: Pre-processors
Classifier: Programming Language :: Python :: 3
Classifier: License :: OSI Approved :: GNU Affero General Public License v3
Classifier: Operating System :: POSIX :: Linux
Requires-Dist: PyPDF2
Requires-Dist: watch-path
